{"entities":{"pages":{"starter":{"id":"starter","title":"Installer WildFly sur la machine","url":"starter.html","level":0,"tabIndex":0},"Configurer-Spring-Boot-pour-générer-des-fichiers-WAR":{"id":"Configurer-Spring-Boot-pour-générer-des-fichiers-WAR","title":"Configurer Spring Boot pour générer des fichiers WAR","url":"configurer-spring-boot-pour-générer-des-fichiers-war.html","level":0,"tabIndex":1},"ed":{"id":"ed","title":"Configurer le fichier `build.gradle`","url":"ed.html","level":0,"tabIndex":2},"kjl":{"id":"kjl","title":"Ajouter et configurer WildFly dans IntelliJ","url":"kjl.html","level":0,"tabIndex":3}}},"topLevelIds":["starter","Configurer-Spring-Boot-pour-générer-des-fichiers-WAR","ed","kjl"]}